ami/__init__.py
ami/account.py
ami/ci.py
ami/conda.py
ami/container.py
ami/cpu.py
ami/databricks.py
ami/envvar.py
ami/github.py
ami/networking.py
ami/os.py
ami/positron.py
ami/power.py
ami/python.py
ami/quarto.py
ami/testing.py
ami/virtualenv.py
ami/vscode.py
ami-0.1.0.dist-info/METADATA
ami-0.1.0.dist-info/WHEEL
ami-0.1.0.dist-info/licenses/LICENSE
ami-0.1.0.dist-info/RECORD
