Metadata-Version: 2.4
Name: ami
Version: 0.1.0
Summary: Simple functions to detect various runtime environments
Project-URL: Repository, https://github.com/briandconnelly/ami-py
Project-URL: Issues, https://github.com/briandconnelly/ami-py/issues
Author-email: Brian Connelly <bdc@bconnelly.net>
License: MIT License
License-File: LICENSE
Keywords: ci,container,detection,environment,runtime,virtualenv
Classifier: Development Status :: 4 - Beta
Classifier: Intended Audience :: Developers
Classifier: License :: OSI Approved :: MIT License
Classifier: Operating System :: OS Independent
Classifier: Programming Language :: Python
Classifier: Programming Language :: Python :: 3
Classifier: Programming Language :: Python :: 3.11
Classifier: Programming Language :: Python :: 3.12
Classifier: Topic :: Software Development :: Libraries :: Python Modules
Classifier: Topic :: System :: Systems Administration
Requires-Python: >=3.11
Requires-Dist: psutil>=6.1.1
